{
  "schemaVersion": "1.0.0",
  "portFamily": "SecretsVaulting",
  "sourceCatalog": "docs/integration-catalog/secrets-vaulting.md",
  "operations": [
    {
      "operation": "getSecret",
      "description": "Retrieve a secret value by path or canonical ID",
      "idempotent": true
    },
    {
      "operation": "putSecret",
      "description": "Create or update a secret at a given path",
      "idempotent": false
    },
    {
      "operation": "deleteSecret",
      "description": "Permanently or soft-delete a secret",
      "idempotent": false
    },
    {
      "operation": "listSecrets",
      "description": "List secret metadata (not values) with optional path prefix filter",
      "idempotent": true
    },
    {
      "operation": "rotateSecret",
      "description": "Trigger immediate rotation of a secret according to its rotation config",
      "idempotent": false
    },
    {
      "operation": "createCertificate",
      "description": "Issue a new certificate from the configured PKI backend",
      "idempotent": false
    },
    {
      "operation": "getCertificate",
      "description": "Retrieve a certificate and its chain by ID or common name",
      "idempotent": true
    },
    {
      "operation": "renewCertificate",
      "description": "Renew an existing certificate before expiry",
      "idempotent": false
    },
    {
      "operation": "listCertificates",
      "description": "List certificates with filter by status, expiry window, or issuer",
      "idempotent": true
    },
    {
      "operation": "encrypt",
      "description": "Encrypt a plaintext payload using a named key",
      "idempotent": true
    },
    {
      "operation": "decrypt",
      "description": "Decrypt a ciphertext payload using a named key",
      "idempotent": true
    },
    {
      "operation": "createKey",
      "description": "Create a new encryption key in the key-management backend",
      "idempotent": false
    },
    {
      "operation": "listKeys",
      "description": "List available encryption keys with metadata",
      "idempotent": true
    },
    {
      "operation": "getAuditLog",
      "description": "Retrieve audit log entries filtered by time range, principal, or action",
      "idempotent": true
    },
    {
      "operation": "setSecretPolicy",
      "description": "Apply or update an access policy governing a secret path or key",
      "idempotent": false
    }
  ]
}
